<?xml version='1.0' encoding='UTF-8'?>
<annotation>
  <filename>00261.jpg</filename>
  <object_num>3</object_num>
  <size>
    <width>605</width>
    <height>403</height>
  </size>
  <object>
    <name>apple</name>
    <difficult>0</difficult>
    <bndbox>
      <xmin>120</xmin>
      <ymin>228</ymin>
      <xmax>237</xmax>
      <ymax>371</ymax>
    </bndbox>
  </object>
  <object>
    <name>apple</name>
    <difficult>0</difficult>
    <bndbox>
      <xmin>127</xmin>
      <ymin>69</ymin>
      <xmax>218</xmax>
      <ymax>179</ymax>
    </bndbox>
  </object>
  <object>
    <name>apple</name>
    <difficult>0</difficult>
    <bndbox>
      <xmin>236</xmin>
      <ymin>68</ymin>
      <xmax>403</xmax>
      <ymax>227</ymax>
    </bndbox>
  </object>
</annotation>
