<?xml version='1.0' encoding='UTF-8'?>
<annotation>
  <filename>00622.jpg</filename>
  <object_num>2</object_num>
  <size>
    <width>1200</width>
    <height>1200</height>
  </size>
  <object>
    <name>apple</name>
    <difficult>0</difficult>
    <bndbox>
      <xmin>1</xmin>
      <ymin>182</ymin>
      <xmax>384</xmax>
      <ymax>709</ymax>
    </bndbox>
  </object>
  <object>
    <name>apple</name>
    <difficult>0</difficult>
    <bndbox>
      <xmin>168</xmin>
      <ymin>540</ymin>
      <xmax>726</xmax>
      <ymax>1110</ymax>
    </bndbox>
  </object>
</annotation>
