<?xml version='1.0' encoding='UTF-8'?>
<annotation>
  <filename>01341.jpg</filename>
  <object_num>3</object_num>
  <size>
    <width>1080</width>
    <height>1455</height>
  </size>
  <object>
    <name>apple</name>
    <difficult>0</difficult>
    <bndbox>
      <xmin>35</xmin>
      <ymin>793</ymin>
      <xmax>81</xmax>
      <ymax>837</ymax>
    </bndbox>
  </object>
  <object>
    <name>apple</name>
    <difficult>0</difficult>
    <bndbox>
      <xmin>0</xmin>
      <ymin>219</ymin>
      <xmax>328</xmax>
      <ymax>668</ymax>
    </bndbox>
  </object>
  <object>
    <name>apple</name>
    <difficult>0</difficult>
    <bndbox>
      <xmin>128</xmin>
      <ymin>526</ymin>
      <xmax>404</xmax>
      <ymax>798</ymax>
    </bndbox>
  </object>
</annotation>
