<?xml version='1.0' encoding='UTF-8'?>
<annotation>
  <filename>01364.jpg</filename>
  <object_num>2</object_num>
  <size>
    <width>800</width>
    <height>800</height>
  </size>
  <object>
    <name>apple</name>
    <difficult>0</difficult>
    <bndbox>
      <xmin>432</xmin>
      <ymin>185</ymin>
      <xmax>800</xmax>
      <ymax>796</ymax>
    </bndbox>
  </object>
  <object>
    <name>apple</name>
    <difficult>0</difficult>
    <bndbox>
      <xmin>2</xmin>
      <ymin>248</ymin>
      <xmax>630</xmax>
      <ymax>795</ymax>
    </bndbox>
  </object>
</annotation>
