<?xml version='1.0' encoding='UTF-8'?>
<annotation>
  <filename>01465.jpg</filename>
  <object_num>2</object_num>
  <size>
    <width>500</width>
    <height>375</height>
  </size>
  <object>
    <name>apple</name>
    <difficult>0</difficult>
    <bndbox>
      <xmin>79</xmin>
      <ymin>68</ymin>
      <xmax>386</xmax>
      <ymax>356</ymax>
    </bndbox>
  </object>
  <object>
    <name>apple</name>
    <difficult>0</difficult>
    <bndbox>
      <xmin>342</xmin>
      <ymin>146</ymin>
      <xmax>483</xmax>
      <ymax>324</ymax>
    </bndbox>
  </object>
</annotation>
