<?xml version='1.0' encoding='UTF-8'?>
<annotation>
  <filename>01577.jpg</filename>
  <object_num>5</object_num>
  <size>
    <width>390</width>
    <height>390</height>
  </size>
  <object>
    <name>apple</name>
    <difficult>0</difficult>
    <bndbox>
      <xmin>121</xmin>
      <ymin>107</ymin>
      <xmax>205</xmax>
      <ymax>200</ymax>
    </bndbox>
  </object>
  <object>
    <name>apple</name>
    <difficult>0</difficult>
    <bndbox>
      <xmin>233</xmin>
      <ymin>199</ymin>
      <xmax>299</xmax>
      <ymax>260</ymax>
    </bndbox>
  </object>
  <object>
    <name>apple</name>
    <difficult>0</difficult>
    <bndbox>
      <xmin>290</xmin>
      <ymin>143</ymin>
      <xmax>373</xmax>
      <ymax>227</ymax>
    </bndbox>
  </object>
  <object>
    <name>apple</name>
    <difficult>0</difficult>
    <bndbox>
      <xmin>76</xmin>
      <ymin>209</ymin>
      <xmax>155</xmax>
      <ymax>283</ymax>
    </bndbox>
  </object>
  <object>
    <name>apple</name>
    <difficult>0</difficult>
    <bndbox>
      <xmin>226</xmin>
      <ymin>311</ymin>
      <xmax>282</xmax>
      <ymax>357</ymax>
    </bndbox>
  </object>
</annotation>
