<?xml version='1.0' encoding='UTF-8'?>
<annotation>
  <filename>01944.jpg</filename>
  <object_num>15</object_num>
  <size>
    <width>1080</width>
    <height>810</height>
  </size>
  <object>
    <name>apple</name>
    <difficult>0</difficult>
    <bndbox>
      <xmin>568</xmin>
      <ymin>462</ymin>
      <xmax>606</xmax>
      <ymax>490</ymax>
    </bndbox>
  </object>
  <object>
    <name>apple</name>
    <difficult>0</difficult>
    <bndbox>
      <xmin>591</xmin>
      <ymin>477</ymin>
      <xmax>633</xmax>
      <ymax>501</ymax>
    </bndbox>
  </object>
  <object>
    <name>apple</name>
    <difficult>0</difficult>
    <bndbox>
      <xmin>301</xmin>
      <ymin>395</ymin>
      <xmax>359</xmax>
      <ymax>444</ymax>
    </bndbox>
  </object>
  <object>
    <name>apple</name>
    <difficult>0</difficult>
    <bndbox>
      <xmin>575</xmin>
      <ymin>499</ymin>
      <xmax>621</xmax>
      <ymax>526</ymax>
    </bndbox>
  </object>
  <object>
    <name>apple</name>
    <difficult>0</difficult>
    <bndbox>
      <xmin>853</xmin>
      <ymin>556</ymin>
      <xmax>906</xmax>
      <ymax>594</ymax>
    </bndbox>
  </object>
  <object>
    <name>apple</name>
    <difficult>0</difficult>
    <bndbox>
      <xmin>391</xmin>
      <ymin>383</ymin>
      <xmax>426</xmax>
      <ymax>413</ymax>
    </bndbox>
  </object>
  <object>
    <name>apple</name>
    <difficult>0</difficult>
    <bndbox>
      <xmin>619</xmin>
      <ymin>490</ymin>
      <xmax>660</xmax>
      <ymax>528</ymax>
    </bndbox>
  </object>
  <object>
    <name>apple</name>
    <difficult>0</difficult>
    <bndbox>
      <xmin>420</xmin>
      <ymin>408</ymin>
      <xmax>465</xmax>
      <ymax>444</ymax>
    </bndbox>
  </object>
  <object>
    <name>apple</name>
    <difficult>0</difficult>
    <bndbox>
      <xmin>512</xmin>
      <ymin>490</ymin>
      <xmax>563</xmax>
      <ymax>527</ymax>
    </bndbox>
  </object>
  <object>
    <name>apple</name>
    <difficult>0</difficult>
    <bndbox>
      <xmin>772</xmin>
      <ymin>362</ymin>
      <xmax>811</xmax>
      <ymax>398</ymax>
    </bndbox>
  </object>
  <object>
    <name>apple</name>
    <difficult>0</difficult>
    <bndbox>
      <xmin>452</xmin>
      <ymin>390</ymin>
      <xmax>499</xmax>
      <ymax>436</ymax>
    </bndbox>
  </object>
  <object>
    <name>apple</name>
    <difficult>0</difficult>
    <bndbox>
      <xmin>649</xmin>
      <ymin>194</ymin>
      <xmax>690</xmax>
      <ymax>225</ymax>
    </bndbox>
  </object>
  <object>
    <name>apple</name>
    <difficult>0</difficult>
    <bndbox>
      <xmin>495</xmin>
      <ymin>383</ymin>
      <xmax>542</xmax>
      <ymax>435</ymax>
    </bndbox>
  </object>
  <object>
    <name>apple</name>
    <difficult>0</difficult>
    <bndbox>
      <xmin>358</xmin>
      <ymin>401</ymin>
      <xmax>402</xmax>
      <ymax>438</ymax>
    </bndbox>
  </object>
  <object>
    <name>apple</name>
    <difficult>0</difficult>
    <bndbox>
      <xmin>657</xmin>
      <ymin>384</ymin>
      <xmax>703</xmax>
      <ymax>417</ymax>
    </bndbox>
  </object>
</annotation>
