<?xml version='1.0' encoding='UTF-8'?>
<annotation>
  <filename>02002.jpg</filename>
  <object_num>4</object_num>
  <size>
    <width>720</width>
    <height>1280</height>
  </size>
  <object>
    <name>apple</name>
    <difficult>0</difficult>
    <bndbox>
      <xmin>1</xmin>
      <ymin>704</ymin>
      <xmax>301</xmax>
      <ymax>1192</ymax>
    </bndbox>
  </object>
  <object>
    <name>apple</name>
    <difficult>0</difficult>
    <bndbox>
      <xmin>276</xmin>
      <ymin>721</ymin>
      <xmax>686</xmax>
      <ymax>1093</ymax>
    </bndbox>
  </object>
  <object>
    <name>apple</name>
    <difficult>0</difficult>
    <bndbox>
      <xmin>251</xmin>
      <ymin>311</ymin>
      <xmax>708</xmax>
      <ymax>757</ymax>
    </bndbox>
  </object>
  <object>
    <name>apple</name>
    <difficult>0</difficult>
    <bndbox>
      <xmin>30</xmin>
      <ymin>106</ymin>
      <xmax>423</xmax>
      <ymax>529</ymax>
    </bndbox>
  </object>
</annotation>
