<?xml version='1.0' encoding='UTF-8'?>
<annotation>
  <filename>02492.jpg</filename>
  <object_num>4</object_num>
  <size>
    <width>600</width>
    <height>400</height>
  </size>
  <object>
    <name>apple</name>
    <difficult>0</difficult>
    <bndbox>
      <xmin>326</xmin>
      <ymin>177</ymin>
      <xmax>417</xmax>
      <ymax>343</ymax>
    </bndbox>
  </object>
  <object>
    <name>apple</name>
    <difficult>0</difficult>
    <bndbox>
      <xmin>1</xmin>
      <ymin>64</ymin>
      <xmax>183</xmax>
      <ymax>247</ymax>
    </bndbox>
  </object>
  <object>
    <name>apple</name>
    <difficult>0</difficult>
    <bndbox>
      <xmin>375</xmin>
      <ymin>97</ymin>
      <xmax>555</xmax>
      <ymax>261</ymax>
    </bndbox>
  </object>
  <object>
    <name>apple</name>
    <difficult>0</difficult>
    <bndbox>
      <xmin>154</xmin>
      <ymin>136</ymin>
      <xmax>374</xmax>
      <ymax>357</ymax>
    </bndbox>
  </object>
</annotation>
