<?xml version='1.0' encoding='UTF-8'?>
<annotation>
  <filename>02859.jpg</filename>
  <object_num>8</object_num>
  <size>
    <width>800</width>
    <height>800</height>
  </size>
  <object>
    <name>apple</name>
    <difficult>0</difficult>
    <bndbox>
      <xmin>553</xmin>
      <ymin>286</ymin>
      <xmax>798</xmax>
      <ymax>521</ymax>
    </bndbox>
  </object>
  <object>
    <name>apple</name>
    <difficult>0</difficult>
    <bndbox>
      <xmin>8</xmin>
      <ymin>567</ymin>
      <xmax>245</xmax>
      <ymax>800</ymax>
    </bndbox>
  </object>
  <object>
    <name>apple</name>
    <difficult>0</difficult>
    <bndbox>
      <xmin>280</xmin>
      <ymin>276</ymin>
      <xmax>524</xmax>
      <ymax>528</ymax>
    </bndbox>
  </object>
  <object>
    <name>apple</name>
    <difficult>0</difficult>
    <bndbox>
      <xmin>555</xmin>
      <ymin>547</ymin>
      <xmax>797</xmax>
      <ymax>781</ymax>
    </bndbox>
  </object>
  <object>
    <name>apple</name>
    <difficult>0</difficult>
    <bndbox>
      <xmin>280</xmin>
      <ymin>546</ymin>
      <xmax>528</xmax>
      <ymax>790</ymax>
    </bndbox>
  </object>
  <object>
    <name>apple</name>
    <difficult>0</difficult>
    <bndbox>
      <xmin>27</xmin>
      <ymin>22</ymin>
      <xmax>264</xmax>
      <ymax>249</ymax>
    </bndbox>
  </object>
  <object>
    <name>apple</name>
    <difficult>0</difficult>
    <bndbox>
      <xmin>291</xmin>
      <ymin>12</ymin>
      <xmax>515</xmax>
      <ymax>252</ymax>
    </bndbox>
  </object>
  <object>
    <name>apple</name>
    <difficult>0</difficult>
    <bndbox>
      <xmin>17</xmin>
      <ymin>284</ymin>
      <xmax>254</xmax>
      <ymax>521</ymax>
    </bndbox>
  </object>
</annotation>
