<?xml version='1.0' encoding='UTF-8'?>
<annotation>
  <filename>03054.jpg</filename>
  <object_num>3</object_num>
  <size>
    <width>800</width>
    <height>800</height>
  </size>
  <object>
    <name>apple</name>
    <difficult>0</difficult>
    <bndbox>
      <xmin>1</xmin>
      <ymin>389</ymin>
      <xmax>336</xmax>
      <ymax>800</ymax>
    </bndbox>
  </object>
  <object>
    <name>apple</name>
    <difficult>0</difficult>
    <bndbox>
      <xmin>145</xmin>
      <ymin>28</ymin>
      <xmax>643</xmax>
      <ymax>522</ymax>
    </bndbox>
  </object>
  <object>
    <name>apple</name>
    <difficult>0</difficult>
    <bndbox>
      <xmin>338</xmin>
      <ymin>447</ymin>
      <xmax>799</xmax>
      <ymax>800</ymax>
    </bndbox>
  </object>
</annotation>
