<?xml version='1.0' encoding='UTF-8'?>
<annotation>
  <filename>03070.jpg</filename>
  <object_num>3</object_num>
  <size>
    <width>680</width>
    <height>510</height>
  </size>
  <object>
    <name>apple</name>
    <difficult>0</difficult>
    <bndbox>
      <xmin>107</xmin>
      <ymin>87</ymin>
      <xmax>501</xmax>
      <ymax>424</ymax>
    </bndbox>
  </object>
  <object>
    <name>apple</name>
    <difficult>0</difficult>
    <bndbox>
      <xmin>98</xmin>
      <ymin>36</ymin>
      <xmax>252</xmax>
      <ymax>158</ymax>
    </bndbox>
  </object>
  <object>
    <name>apple</name>
    <difficult>0</difficult>
    <bndbox>
      <xmin>570</xmin>
      <ymin>26</ymin>
      <xmax>680</xmax>
      <ymax>168</ymax>
    </bndbox>
  </object>
</annotation>
