<?xml version='1.0' encoding='UTF-8'?>
<annotation>
  <filename>03280.jpg</filename>
  <object_num>5</object_num>
  <size>
    <width>540</width>
    <height>960</height>
  </size>
  <object>
    <name>apple</name>
    <difficult>0</difficult>
    <bndbox>
      <xmin>283</xmin>
      <ymin>723</ymin>
      <xmax>500</xmax>
      <ymax>901</ymax>
    </bndbox>
  </object>
  <object>
    <name>apple</name>
    <difficult>0</difficult>
    <bndbox>
      <xmin>1</xmin>
      <ymin>250</ymin>
      <xmax>224</xmax>
      <ymax>531</ymax>
    </bndbox>
  </object>
  <object>
    <name>apple</name>
    <difficult>0</difficult>
    <bndbox>
      <xmin>23</xmin>
      <ymin>2</ymin>
      <xmax>249</xmax>
      <ymax>211</ymax>
    </bndbox>
  </object>
  <object>
    <name>apple</name>
    <difficult>0</difficult>
    <bndbox>
      <xmin>412</xmin>
      <ymin>515</ymin>
      <xmax>540</xmax>
      <ymax>722</ymax>
    </bndbox>
  </object>
  <object>
    <name>apple</name>
    <difficult>0</difficult>
    <bndbox>
      <xmin>101</xmin>
      <ymin>483</ymin>
      <xmax>448</xmax>
      <ymax>811</ymax>
    </bndbox>
  </object>
</annotation>
