<?xml version='1.0' encoding='UTF-8'?>
<annotation>
  <filename>03826.jpg</filename>
  <object_num>2</object_num>
  <size>
    <width>1440</width>
    <height>1080</height>
  </size>
  <object>
    <name>apple</name>
    <difficult>0</difficult>
    <bndbox>
      <xmin>44</xmin>
      <ymin>285</ymin>
      <xmax>341</xmax>
      <ymax>564</ymax>
    </bndbox>
  </object>
  <object>
    <name>apple</name>
    <difficult>0</difficult>
    <bndbox>
      <xmin>388</xmin>
      <ymin>505</ymin>
      <xmax>661</xmax>
      <ymax>765</ymax>
    </bndbox>
  </object>
</annotation>
