<?xml version='1.0' encoding='UTF-8'?>
<annotation>
  <filename>04612.jpg</filename>
  <object_num>3</object_num>
  <size>
    <width>256</width>
    <height>256</height>
  </size>
  <object>
    <name>apple</name>
    <difficult>0</difficult>
    <bndbox>
      <xmin>74</xmin>
      <ymin>57</ymin>
      <xmax>147</xmax>
      <ymax>144</ymax>
    </bndbox>
  </object>
  <object>
    <name>apple</name>
    <difficult>0</difficult>
    <bndbox>
      <xmin>114</xmin>
      <ymin>95</ymin>
      <xmax>183</xmax>
      <ymax>194</ymax>
    </bndbox>
  </object>
  <object>
    <name>apple</name>
    <difficult>0</difficult>
    <bndbox>
      <xmin>38</xmin>
      <ymin>94</ymin>
      <xmax>117</xmax>
      <ymax>202</ymax>
    </bndbox>
  </object>
</annotation>
